odoo/addons/stock_dock/README.rst
odoo/addons/stock_dock/__init__.py
odoo/addons/stock_dock/__manifest__.py
odoo/addons/stock_dock/demo/stock_dock.xml
odoo/addons/stock_dock/i18n/es.po
odoo/addons/stock_dock/i18n/fr.po
odoo/addons/stock_dock/i18n/it.po
odoo/addons/stock_dock/i18n/pt_BR.po
odoo/addons/stock_dock/i18n/stock_dock.pot
odoo/addons/stock_dock/models/__init__.py
odoo/addons/stock_dock/models/stock_dock.py
odoo/addons/stock_dock/readme/CONTRIBUTORS.md
odoo/addons/stock_dock/readme/CREDITS.md
odoo/addons/stock_dock/readme/DESCRIPTION.md
odoo/addons/stock_dock/security/ir.model.access.csv
odoo/addons/stock_dock/static/description/icon.png
odoo/addons/stock_dock/static/description/index.html
odoo/addons/stock_dock/tests/__init__.py
odoo/addons/stock_dock/tests/test_stock_dock.py
odoo/addons/stock_dock/views/stock_dock.xml
odoo_addon_stock_dock-18.0.1.1.0.1.dist-info/METADATA
odoo_addon_stock_dock-18.0.1.1.0.1.dist-info/WHEEL
odoo_addon_stock_dock-18.0.1.1.0.1.dist-info/top_level.txt
odoo_addon_stock_dock-18.0.1.1.0.1.dist-info/RECORD
